cantact/__init__.py
cantact/cantact.cp311-win_amd64.pyd
cantact-0.1.3.dist-info/METADATA
cantact-0.1.3.dist-info/WHEEL
cantact-0.1.3.dist-info/top_level.txt
cantact-0.1.3.dist-info/RECORD
