Metadata-Version: 2.1
Name: cantact
Version: 0.1.3
Summary: Support for the CANtact Controller Area Network Devices
Home-page: https://github.com/linklayer/cantact
Author: Eric Evenchick
Author-email: eric@evenchick.com
Classifier: License :: OSI Approved :: MIT License
Classifier: Development Status :: 3 - Alpha
Classifier: Intended Audience :: Developers
Classifier: Programming Language :: Python
Classifier: Programming Language :: Rust
Classifier: Operating System :: POSIX :: Linux
Classifier: Operating System :: MacOS :: MacOS X
Classifier: Operating System :: Microsoft :: Windows
Classifier: Topic :: System :: Hardware :: Hardware Drivers
Classifier: Topic :: System :: Networking
Classifier: Topic :: Software Development :: Embedded Systems
Requires-Python: >=3.5
